rev_deps/__about__.py
rev_deps/__init__.py
rev_deps/__main__.py
rev_deps/api.py
rev_deps/cli.py
rev_deps/core.py
rev_deps-0.0.3.dist-info/METADATA
rev_deps-0.0.3.dist-info/WHEEL
rev_deps-0.0.3.dist-info/entry_points.txt
rev_deps-0.0.3.dist-info/licenses/LICENSE.txt
rev_deps-0.0.3.dist-info/RECORD
