Metadata-Version: 2.4
Name: rev-deps
Version: 0.0.3
Summary: Find the names of all the projects that depend on another project, using Wheelodex.
Project-URL: Issues, https://github.com/JamesParrott/rev-deps/issues
Project-URL: Source, https://github.com/JamesParrott/rev-deps
Author-email: James Parrott <james.parrott@proton.me>
License: MIT License
License-File: LICENSE.txt
Classifier: Development Status :: 4 - Beta
Classifier: Programming Language :: Python
Classifier: Programming Language :: Python :: 3
Classifier: Programming Language :: Python :: Implementation :: CPython
Requires-Python: >=3.8
Requires-Dist: requests
